dh_testers/__init__.py
dh_testers/common.py
dh_testers/commonTest.py
dh_testers/coverageProject.py
dh_testers/externalAll.py
dh_testers/findNonUTF8.py
dh_testers/memoryUsage.py
dh_testers/multiprocess.py
dh_testers/singleCore.py
dh_testers/testLint.py
dh_testers/testRunner.py
dh_testers/treeYield.py
dh_testers/warningMultiprocess.py
dh_testers-0.1.0.dist-info/METADATA
dh_testers-0.1.0.dist-info/RECORD
dh_testers-0.1.0.dist-info/WHEEL
dh_testers-0.1.0.dist-info/top_level.txt
