Metadata-Version: 2.1
Name: dh-testers
Version: 0.1.0
Summary: Testing module for projects, including dh
Home-page: https://github.com/dhmit/dh_testers
Author: Michael Scott Cuthbert
Author-email: cuthbert@mit.edu
License: UNKNOWN
Platform: UNKNOWN
Classifier: Programming Language :: Python :: 3
Classifier: License :: OSI Approved :: BSD License
Classifier: Operating System :: OS Independent
